<OutOfBrowserSettings ShortName="RCC Help Desk Ticketing Administration" EnableGPUAcceleration="False" ShowInstallMenuItem="True">
  <OutOfBrowserSettings.Blurb>RCC Help Desk Ticketing Administration</OutOfBrowserSettings.Blurb>
  <OutOfBrowserSettings.WindowSettings>
    <WindowSettings Title="RCC Help Desk Ticketing Administration" Top="0" Left="0" WindowStartupLocation="Manual" />
  </OutOfBrowserSettings.WindowSettings>
  <OutOfBrowserSettings.SecuritySettings>
    <SecuritySettings ElevatedPermissions="Required" />
  </OutOfBrowserSettings.SecuritySettings>
  <OutOfBrowserSettings.Icons>
    <Icon Size="32,32">Resources/user-logo.png</Icon>
  </OutOfBrowserSettings.Icons>
</OutOfBrowserSettings>